instapy/__init__.py
instapy/browser.py
instapy/clarifai_util.py
instapy/comment_util.py
instapy/commenters_util.py
instapy/constants.py
instapy/database_engine.py
instapy/event.py
instapy/exceptions.py
instapy/feed_util.py
instapy/file_manager.py
instapy/follow_util.py
instapy/instapy.py
instapy/like_util.py
instapy/login_util.py
instapy/monkey_patcher.py
instapy/pods_util.py
instapy/print_log_writer.py
instapy/quota_supervisor.py
instapy/relationship_tools.py
instapy/settings.py
instapy/story_util.py
instapy/text_analytics.py
instapy/time_util.py
instapy/unfollow_util.py
instapy/util.py
instapy/xpath.py
instapy/xpath_compile.py
instapy/firefox_extension/arrive.js
instapy/firefox_extension/content.js
instapy/firefox_extension/manifest.json
instapy/icons/Linux/qs_exit_linux.png
instapy/icons/Linux/qs_sleep_linux.png
instapy/icons/Linux/qs_wakeup_linux.png
instapy/icons/Mac/qs_exit_mac.icns
instapy/icons/Mac/qs_sleep_mac.icns
instapy/icons/Mac/qs_wakeup_mac.icns
instapy/icons/Windows/qs_exit_windows.ico
instapy/icons/Windows/qs_sleep_windows.ico
instapy/icons/Windows/qs_wakeup_windows.ico
instapy/plugins/__init__.py
instapy/plugins/telegram_util.py
instapy-0.6.16.dist-info/LICENSE
instapy-0.6.16.dist-info/METADATA
instapy-0.6.16.dist-info/WHEEL
instapy-0.6.16.dist-info/entry_points.txt
instapy-0.6.16.dist-info/top_level.txt
instapy-0.6.16.dist-info/RECORD
