Metadata-Version: 2.1
Name: instapy
Version: 0.6.16
Summary: Tool for automated Instagram interactions
Home-page: https://github.com/timgrossmann/InstaPy
Author: Tim Großmann
Author-email: contact.timgrossmann@gmail.com
Maintainer: InstaPy Community at Github
License: GPLv3
Download-URL: https://github.com/timgrossmann/InstaPy/archive/master.zip
Project-URL: How Tos, https://github.com/timgrossmann/InstaPy/tree/master/docs
Project-URL: Examples, https://github.com/timgrossmann/InstaPy/tree/master/quickstart_templates
Project-URL: Bug Reports, https://github.com/timgrossmann/InstaPy/issues
Project-URL: Funding, https://www.paypal.me/supportInstaPy
Project-URL: Say Thanks!, http://saythanks.io/to/uluQulu
Project-URL: Source, https://github.com/timgrossmann/InstaPy/tree/master/instapy
Keywords: instapy python instagram automation          marketing promotion bot selenium
Platform: win32
Platform: linux
Platform: linux2
Platform: darwin
Classifier: Development Status :: 4 - Beta
Classifier: Environment :: Console
Classifier: Environment :: Win32 (MS Windows)
Classifier: Environment :: MacOS X
Classifier: Environment :: Web Environment
Classifier: Intended Audience :: End Users/Desktop
Classifier: Intended Audience :: Developers
Classifier: Operating System :: Microsoft :: Windows
Classifier: Operating System :: POSIX :: Linux
Classifier: Operating System :: MacOS :: MacOS X
Classifier: Operating System :: Unix
Classifier: Programming Language :: Python
Classifier: Programming Language :: JavaScript
Classifier: Programming Language :: SQL
Classifier: Topic :: Utilities
Classifier: Topic :: Software Development :: Build Tools
Classifier: Programming Language :: Python :: 3
Classifier: Programming Language :: Python :: 3.5
Classifier: Programming Language :: Python :: 3.6
Classifier: Programming Language :: Python :: 3.7
Classifier: Programming Language :: Python :: 3.8
Classifier: Programming Language :: Python :: 3.9
Classifier: Natural Language :: English
Requires-Python: >=3.5
Provides-Extra: test
License-File: LICENSE
